atramhasis/__init__.py
atramhasis/audit.py
atramhasis/db.py
atramhasis/errors.py
atramhasis/mappers.py
atramhasis/models.py
atramhasis/protected_resources.py
atramhasis/rdf.py
atramhasis/renderers.py
atramhasis/routes.py
atramhasis/service.py
atramhasis/utils.py
atramhasis/validators.py
atramhasis/alembic/README
atramhasis/alembic/env.py
atramhasis/alembic/env.pyc
atramhasis/alembic/script.py.mako
atramhasis/alembic/versions/184f1bbcb916_language_und.py
atramhasis/alembic/versions/1a4d62b02630_199_sources.py
atramhasis/alembic/versions/1a4d62b02630_199_sources.pyc
atramhasis/alembic/versions/1ad2b6fbcf22_visit_log.py
atramhasis/alembic/versions/1ad2b6fbcf22_visit_log.pyc
atramhasis/alembic/versions/2a38d364113b_languages_for_conceptschemes.py
atramhasis/alembic/versions/2a38d364113b_languages_for_conceptschemes.pyc
atramhasis/alembic/versions/3924a7ad2f8_init.py
atramhasis/alembic/versions/3924a7ad2f8_init.pyc
atramhasis/alembic/versions/3ac8aca026fd_note_markup.py
atramhasis/alembic/versions/3ac8aca026fd_note_markup.pyc
atramhasis/alembic/versions/3bcf11802900_add_markup_to_source.py
atramhasis/alembic/versions/3bcf11802900_add_markup_to_source.pyc
atramhasis/alembic/versions/441c5a16ef8_add_skos_matches.py
atramhasis/alembic/versions/441c5a16ef8_add_skos_matches.pyc
atramhasis/alembic/versions/4f1ee5c9c08_init_skos_data.py
atramhasis/alembic/versions/4f1ee5c9c08_init_skos_data.pyc
atramhasis/alembic/versions/5e15729b574d_toevoegen_timezones.pyc
atramhasis/alembic/versions/6dfc3e2324aa_add_sortlabel.py
atramhasis/alembic/versions/b04fd493106b_add_conceptscheme_counts.py
atramhasis/cache/__init__.py
atramhasis/data/__init__.py
atramhasis/data/datamanagers.py
atramhasis/data/db.py
atramhasis/data/models.py
atramhasis/locale/atramhasis.pot
atramhasis/locale/en/LC_MESSAGES/atramhasis.po
atramhasis/locale/fr/LC_MESSAGES/atramhasis.po
atramhasis/locale/nl/LC_MESSAGES/atramhasis.po
atramhasis/scaffolds/__init__.py
atramhasis-0.6.6.dist-info/DESCRIPTION.rst
atramhasis-0.6.6.dist-info/METADATA
atramhasis-0.6.6.dist-info/RECORD
atramhasis-0.6.6.dist-info/WHEEL
atramhasis-0.6.6.dist-info/entry_points.txt
atramhasis-0.6.6.dist-info/metadata.json
atramhasis-0.6.6.dist-info/pbr.json
atramhasis-0.6.6.dist-info/top_level.txt
