Metadata-Version: 2.0
Name: atramhasis
Version: 0.6.6
Summary: A web based editor for thesauri adhering to the SKOS specification.
Home-page: http://atramhasis.readthedocs.org
Author: Flanders Heritage Agency
Author-email: ict@onroerenderfgoed.be
License: GPLv3
Keywords: web wsgi pyramid SKOS thesaurus vocabulary
Platform: UNKNOWN
Classifier: Development Status :: 4 - Beta
Classifier: License :: OSI Approved :: GNU General Public License v3 (GPLv3)
Classifier: Programming Language :: Python
Classifier: Framework :: Pyramid
Classifier: Topic :: Internet :: WWW/HTTP
Classifier: Topic :: Internet :: WWW/HTTP :: WSGI :: Application
Classifier: Programming Language :: Python :: 2.7
Classifier: Programming Language :: Python :: 3.4
Classifier: Programming Language :: Python :: 3.5
Classifier: Programming Language :: Python :: 3.6
Requires-Dist: SQLAlchemy
Requires-Dist: alembic
Requires-Dist: babel
Requires-Dist: colander
Requires-Dist: dogpile.cache
Requires-Dist: language-tags
Requires-Dist: pyramid
Requires-Dist: pyramid-jinja2
Requires-Dist: pyramid-rewrite
Requires-Dist: pyramid-skosprovider
Requires-Dist: pyramid-tm
Requires-Dist: requests
Requires-Dist: six
Requires-Dist: skosprovider
Requires-Dist: skosprovider-getty
Requires-Dist: skosprovider-heritagedata
Requires-Dist: skosprovider-rdf
Requires-Dist: skosprovider-sqlalchemy
Requires-Dist: transaction
Requires-Dist: waitress
Requires-Dist: zope.sqlalchemy
